__init__.py
andromedaClient.py
andromedaClient-0.0.8.dist-info/METADATA
andromedaClient-0.0.8.dist-info/WHEEL
andromedaClient-0.0.8.dist-info/top_level.txt
andromedaClient-0.0.8.dist-info/RECORD
