Metadata-Version: 2.2
Name: andromedaClient
Version: 0.0.8
Summary: A python package to interact with the Andromeda API of the Metropolitan Region Rhine-Neckar.
Author-email: Julian Vetter <julian.vetter@m-r-n.com>
Classifier: Programming Language :: Python :: 3
Classifier: License :: OSI Approved :: MIT License
Classifier: Operating System :: OS Independent
Requires-Python: >=3.8
Requires-Dist: requests
